[
    {
      "id": 1,
      "name": "权限管理",
      "parentId": 0,
      "url": null,
      "perms": null,
      "type": 0,
      "icon": "el-icon-ali-quanxianguanli",
      "orderNum": 0,
      "isShow": true,
      "delFlag": 0,
      "createdBy": null,
      "updatedBy": null,
      "level": 1,
      "children": [
        {
          "id": 2,
          "name": "用户管理",
          "parentId": 1,
          "url": "permission/sys_user.vue",
          "perms": "permission:sys_user",
          "type": 1,
          "icon": "el-icon-ali-guanliyuan",
          "orderNum": 1,
          "isShow": true,
          "delFlag": 0,
          "createdBy": null,
          "updatedBy": null,
          "level": 2,
          "parentName": "权限管理",
          "children": []
        },
        {
          "id": 4,
          "name": "角色管理",
          "parentId": 1,
          "url": "permission/role.vue",
          "perms": "permission:role",
          "type": 1,
          "icon": "el-icon-ali-jiaose",
          "orderNum": 4,
          "isShow": true,
          "delFlag": 0,
          "createdBy": null,
          "updatedBy": null,
          "level": 2,
          "parentName": "权限管理",
          "children": []
        },
        {
          "id": 5,
          "name": "菜单管理",
          "parentId": 1,
          "url": "permission/menu.vue",
          "perms": "permission:menu",
          "type": 1,
          "icon": "el-icon-ali-caidan1",
          "orderNum": 5,
          "isShow": true,
          "delFlag": 0,
          "createdBy": null,
          "updatedBy": null,
          "level": 2,
          "parentName": "权限管理",
          "children": []
        },
        {
          "id": 7,
          "name": "字典管理",
          "parentId": 1,
          "url": "system/dict.vue",
          "perms": "system:dict",
          "type": 1,
          "icon": "el-icon-ali-ccgl-shujuzidian-6",
          "orderNum": 7,
          "isShow": true,
          "delFlag": 0,
          "createdBy": null,
          "updatedBy": null,
          "level": 2,
          "parentName": "权限管理",
          "children": []
        },
        {
          "id": 8,
          "name": "系统日志",
          "parentId": 1,
          "url": "system/log.vue",
          "perms": "system:log",
          "type": 1,
          "icon": "el-icon-ali-system-log",
          "orderNum": 8,
          "isShow": true,
          "delFlag": 0,
          "createdBy": null,
          "updatedBy": null,
          "level": 2,
          "parentName": "权限管理",
          "children": []
        }
      ]
    },
    {
      "id": 250,
      "name": "订单管理",
      "parentId": 0,
      "url": "",
      "perms": "",
      "type": 0,
      "icon": "el-icon-ali-dingdanguanli",
      "orderNum": 0,
      "isShow": true,
      "delFlag": 0,
      "createdBy": null,
      "updatedBy": null,
      "level": 1,
      "children": [
        {
          "id": 251,
          "name": "订单列表",
          "parentId": 250,
          "url": "order/index.vue",
          "perms": "order",
          "type": 1,
          "icon": "el-icon-ali-dingdanliebiao",
          "orderNum": 0,
          "isShow": true,
          "delFlag": 0,
          "createdBy": null,
          "updatedBy": null,
          "level": 2,
          "parentName": "订单管理",
          "children": []
        },
        {
          "id": 252,
          "name": "发货单",
          "parentId": 250,
          "url": "order/delivery.vue",
          "perms": "order:delivery",
          "type": 1,
          "icon": "el-icon-ali-fahuodan",
          "orderNum": 1,
          "isShow": true,
          "delFlag": 0,
          "createdBy": null,
          "updatedBy": null,
          "level": 2,
          "parentName": "订单管理",
          "children": []
        },
        {
          "id": 253,
          "name": "提货单",
          "parentId": 250,
          "url": "order/lading.vue",
          "perms": "order:lading",
          "type": 1,
          "icon": "el-icon-ali-tihuodan",
          "orderNum": 2,
          "isShow": true,
          "delFlag": 0,
          "createdBy": null,
          "updatedBy": null,
          "level": 2,
          "parentName": "订单管理",
          "children": []
        },
        {
          "id": 259,
          "name": "售后单",
          "parentId": 250,
          "url": "order/after_sale.vue",
          "perms": "order:after_sale",
          "type": 1,
          "icon": "el-icon-ali-dingdandefuben",
          "orderNum": 3,
          "isShow": true,
          "delFlag": 0,
          "createdBy": null,
          "updatedBy": null,
          "level": 2,
          "parentName": "订单管理",
          "children": []
        },
        {
          "id": 255,
          "name": "退货单",
          "parentId": 250,
          "url": "order/reship.vue",
          "perms": "order:reship",
          "type": 1,
          "icon": "el-icon-ali-tuihuodan",
          "orderNum": 4,
          "isShow": true,
          "delFlag": 0,
          "createdBy": null,
          "updatedBy": null,
          "level": 2,
          "parentName": "订单管理",
          "children": []
        }
      ]
    },
    {
      "id": 138,
      "name": "商品管理",
      "parentId": 0,
      "url": "",
      "perms": "",
      "type": 0,
      "icon": "el-icon-ali-shangpinguanli",
      "orderNum": 1,
      "isShow": true,
      "delFlag": 0,
      "createdBy": null,
      "updatedBy": null,
      "level": 1,
      "children": [
        {
          "id": 139,
          "name": "商品分类",
          "parentId": 138,
          "url": "goods/goods_cat.vue",
          "perms": "goods:goods_cat",
          "type": 1,
          "icon": "el-icon-ali-shangpinfenlei",
          "orderNum": 0,
          "isShow": true,
          "delFlag": 0,
          "createdBy": null,
          "updatedBy": null,
          "level": 2,
          "parentName": "商品管理",
          "children": []
        },
        {
          "id": 140,
          "name": "品牌管理",
          "parentId": 138,
          "url": "goods/brand.vue",
          "perms": "goods:brand",
          "type": 1,
          "icon": "el-icon-ali-pinpaiguanli",
          "orderNum": 0,
          "isShow": true,
          "delFlag": 0,
          "createdBy": null,
          "updatedBy": null,
          "level": 2,
          "parentName": "商品管理",
          "children": []
        },
        {
          "id": 141,
          "name": "商品属性",
          "parentId": 138,
          "url": "goods/goods_spec.vue",
          "perms": "goods:goods_spec",
          "type": 1,
          "icon": "el-icon-ali-guige",
          "orderNum": 0,
          "isShow": true,
          "delFlag": 0,
          "createdBy": null,
          "updatedBy": null,
          "level": 2,
          "parentName": "商品管理",
          "children": []
        },
        {
          "id": 191,
          "name": "商品参数",
          "parentId": 138,
          "url": "goods/goods_param.vue",
          "perms": "goods:goods_param",
          "type": 1,
          "icon": "el-icon-ali-shangpincanshu",
          "orderNum": 0,
          "isShow": true,
          "delFlag": 0,
          "createdBy": null,
          "updatedBy": null,
          "level": 2,
          "parentName": "商品管理",
          "children": []
        },
        {
          "id": 196,
          "name": "商品类型",
          "parentId": 138,
          "url": "goods/goods_type.vue",
          "perms": "goods:goods_type",
          "type": 1,
          "icon": "el-icon-ali-mendianzuoye-xitongtubiao-",
          "orderNum": 0,
          "isShow": true,
          "delFlag": 0,
          "createdBy": null,
          "updatedBy": null,
          "level": 2,
          "parentName": "商品管理",
          "children": []
        },
        {
          "id": 201,
          "name": "商品评论",
          "parentId": 138,
          "url": "goods/goods_comment.vue",
          "perms": "goods:goods_comment",
          "type": 1,
          "icon": "el-icon-ali-shangpinpinglun",
          "orderNum": 0,
          "isShow": true,
          "delFlag": 0,
          "createdBy": null,
          "updatedBy": null,
          "level": 2,
          "parentName": "商品管理",
          "children": []
        },
        {
          "id": 206,
          "name": "商品列表",
          "parentId": 138,
          "url": "goods/index.vue",
          "perms": "goods",
          "type": 1,
          "icon": "el-icon-ali-shangpinliebiao",
          "orderNum": 0,
          "isShow": true,
          "delFlag": 0,
          "createdBy": null,
          "updatedBy": null,
          "level": 2,
          "parentName": "商品管理",
          "children": []
        }
      ]
    },
    {
      "id": 212,
      "name": "控制面板",
      "parentId": 0,
      "url": "",
      "perms": "",
      "type": 0,
      "icon": "el-icon-ali-kongzhimianban",
      "orderNum": 2,
      "isShow": true,
      "delFlag": 0,
      "createdBy": null,
      "updatedBy": null,
      "level": 1,
      "children": [
        {
          "id": 213,
          "name": "平台设置",
          "parentId": 212,
          "url": "preference/setting.vue",
          "perms": "preference:setting",
          "type": 1,
          "icon": "el-icon-ali-platform-setting",
          "orderNum": 0,
          "isShow": true,
          "delFlag": 0,
          "createdBy": null,
          "updatedBy": null,
          "level": 2,
          "parentName": "控制面板",
          "children": []
        },
        {
          "id": 214,
          "name": "管理员日志",
          "parentId": 212,
          "url": "preference/operation_log.vue",
          "perms": "preference:operation_log",
          "type": 1,
          "icon": "el-icon-ali-rizhi",
          "orderNum": 0,
          "isShow": true,
          "delFlag": 0,
          "createdBy": null,
          "updatedBy": null,
          "level": 2,
          "parentName": "控制面板",
          "children": []
        },
        {
          "id": 215,
          "name": "配送方式",
          "parentId": 212,
          "url": "preference/ship.vue",
          "perms": "preference:ship",
          "type": 1,
          "icon": "el-icon-ali-peisongfangshi",
          "orderNum": 0,
          "isShow": true,
          "delFlag": 0,
          "createdBy": null,
          "updatedBy": null,
          "level": 2,
          "parentName": "控制面板",
          "children": []
        },
        {
          "id": 220,
          "name": "门店管理",
          "parentId": 212,
          "url": "preference/store.vue",
          "perms": "preference:store",
          "type": 1,
          "icon": "el-icon-ali-mendian",
          "orderNum": 0,
          "isShow": true,
          "delFlag": 0,
          "createdBy": null,
          "updatedBy": null,
          "level": 2,
          "parentName": "控制面板",
          "children": []
        },
        {
          "id": 225,
          "name": "任务列表",
          "parentId": 212,
          "url": "preference/task.vue",
          "perms": "preference:task",
          "type": 1,
          "icon": "el-icon-ali-renwu",
          "orderNum": 0,
          "isShow": true,
          "delFlag": 0,
          "createdBy": null,
          "updatedBy": null,
          "level": 2,
          "parentName": "控制面板",
          "children": []
        },
        {
          "id": 228,
          "name": "消息配置",
          "parentId": 212,
          "url": "preference/message_center.vue",
          "perms": "preference:message_center",
          "type": 1,
          "icon": "el-icon-ali-xiaoxipeizhi",
          "orderNum": 0,
          "isShow": true,
          "delFlag": 0,
          "createdBy": null,
          "updatedBy": null,
          "level": 2,
          "parentName": "控制面板",
          "children": []
        },
        {
          "id": 229,
          "name": "区域管理",
          "parentId": 212,
          "url": "preference/area.vue",
          "perms": "preference:area",
          "type": 1,
          "icon": "el-icon-ali-left_menu_area",
          "orderNum": 0,
          "isShow": true,
          "delFlag": 0,
          "createdBy": null,
          "updatedBy": null,
          "level": 2,
          "parentName": "控制面板",
          "children": []
        },
        {
          "id": 234,
          "name": "物流管理",
          "parentId": 212,
          "url": "preference/logistics.vue",
          "perms": "preference:logistics",
          "type": 1,
          "icon": "el-icon-ali-wuliuguanli",
          "orderNum": 0,
          "isShow": true,
          "delFlag": 0,
          "createdBy": null,
          "updatedBy": null,
          "level": 2,
          "parentName": "控制面板",
          "children": []
        }
      ]
    },
    {
      "id": 142,
      "name": "会员管理",
      "parentId": 0,
      "url": "",
      "perms": "",
      "type": 0,
      "icon": "el-icon-ali-huiyuanguanli",
      "orderNum": 3,
      "isShow": true,
      "delFlag": 0,
      "createdBy": null,
      "updatedBy": null,
      "level": 1,
      "children": [
        {
          "id": 143,
          "name": "用户等级",
          "parentId": 142,
          "url": "user/user_grade.vue",
          "perms": "user:user_grade:list",
          "type": 1,
          "icon": "el-icon-ali-213yonghu_dengji4",
          "orderNum": 0,
          "isShow": true,
          "delFlag": 0,
          "createdBy": null,
          "updatedBy": null,
          "level": 2,
          "parentName": "会员管理",
          "children": []
        },
        {
          "id": 144,
          "name": "用户列表",
          "parentId": 142,
          "url": "user/index.vue",
          "perms": "user:list",
          "type": 1,
          "icon": "el-icon-ali-icon-test",
          "orderNum": 0,
          "isShow": true,
          "delFlag": 0,
          "createdBy": null,
          "updatedBy": null,
          "level": 2,
          "parentName": "会员管理",
          "children": []
        }
      ]
    },
    {
      "id": 145,
      "name": "财务管理",
      "parentId": 0,
      "url": "",
      "perms": "",
      "type": 0,
      "icon": "el-icon-ali-caiwuguanli",
      "orderNum": 4,
      "isShow": true,
      "delFlag": 0,
      "createdBy": null,
      "updatedBy": null,
      "level": 1,
      "children": [
        {
          "id": 146,
          "name": "支付方式",
          "parentId": 145,
          "url": "pay/inex.vue",
          "perms": "pay",
          "type": 1,
          "icon": "el-icon-ali-zhifufangshi",
          "orderNum": 0,
          "isShow": true,
          "delFlag": 0,
          "createdBy": null,
          "updatedBy": null,
          "level": 2,
          "parentName": "财务管理",
          "children": []
        },
        {
          "id": 147,
          "name": "支付单",
          "parentId": 145,
          "url": "pay/bill_payment.vue",
          "perms": "pay:bill_payment",
          "type": 1,
          "icon": "el-icon-ali-zhifudan",
          "orderNum": 0,
          "isShow": true,
          "delFlag": 0,
          "createdBy": null,
          "updatedBy": null,
          "level": 2,
          "parentName": "财务管理",
          "children": []
        },
        {
          "id": 148,
          "name": "提现单",
          "parentId": 145,
          "url": "pay/user_to_cash.vue",
          "perms": "pay:user_to_cash",
          "type": 1,
          "icon": "el-icon-ali-tixian",
          "orderNum": 0,
          "isShow": true,
          "delFlag": 0,
          "createdBy": null,
          "updatedBy": null,
          "level": 2,
          "parentName": "财务管理",
          "children": []
        },
        {
          "id": 149,
          "name": "退款单",
          "parentId": 145,
          "url": "pay/bill_refund.vue",
          "perms": "pay:bill_refund",
          "type": 1,
          "icon": "el-icon-ali-tuikuan",
          "orderNum": 0,
          "isShow": true,
          "delFlag": 0,
          "createdBy": null,
          "updatedBy": null,
          "level": 2,
          "parentName": "财务管理",
          "children": []
        },
        {
          "id": 263,
          "name": "帐户流水",
          "parentId": 145,
          "url": "pay/balance.vue",
          "perms": "pay:balance",
          "type": 1,
          "icon": "el-icon-ali-zijinliushui",
          "orderNum": 0,
          "isShow": true,
          "delFlag": 0,
          "createdBy": null,
          "updatedBy": null,
          "level": 2,
          "parentName": "财务管理",
          "children": []
        }
      ]
    },
    {
      "id": 150,
      "name": "市场运营",
      "parentId": 0,
      "url": "",
      "perms": "",
      "type": 0,
      "icon": "el-icon-ali-tuiguang-copy",
      "orderNum": 5,
      "isShow": true,
      "delFlag": 0,
      "createdBy": null,
      "updatedBy": null,
      "level": 1,
      "children": [
        {
          "id": 151,
          "name": "文章分类",
          "parentId": 150,
          "url": "marketing/article_type.vue",
          "perms": "marketing:article_type",
          "type": 1,
          "icon": "el-icon-ali-wenzhangfenlei",
          "orderNum": 0,
          "isShow": true,
          "delFlag": 0,
          "createdBy": null,
          "updatedBy": null,
          "level": 2,
          "parentName": "市场运营",
          "children": []
        },
        {
          "id": 153,
          "name": "文章管理",
          "parentId": 150,
          "url": "marketing/article.vue",
          "perms": "marketing:article",
          "type": 1,
          "icon": "el-icon-ali-wenzhangguanli1",
          "orderNum": 0,
          "isShow": true,
          "delFlag": 0,
          "createdBy": null,
          "updatedBy": null,
          "level": 2,
          "parentName": "市场运营",
          "children": []
        },
        {
          "id": 154,
          "name": "系统公告",
          "parentId": 150,
          "url": "marketing/notice.vue",
          "perms": "marketing:notice",
          "type": 1,
          "icon": "el-icon-ali-xitonggonggao",
          "orderNum": 0,
          "isShow": true,
          "delFlag": 0,
          "createdBy": null,
          "updatedBy": null,
          "level": 2,
          "parentName": "市场运营",
          "children": []
        },
        {
          "id": 155,
          "name": "广告位",
          "parentId": 150,
          "url": "marketing/advert_position.vue",
          "perms": "marketing:advert_position",
          "type": 1,
          "icon": "el-icon-ali-guanggaowei",
          "orderNum": 0,
          "isShow": true,
          "delFlag": 0,
          "createdBy": null,
          "updatedBy": null,
          "level": 2,
          "parentName": "市场运营",
          "children": []
        },
        {
          "id": 156,
          "name": "广告管理",
          "parentId": 150,
          "url": "marketing/advertisement.vue",
          "perms": "marketing:advertisement",
          "type": 1,
          "icon": "el-icon-ali-guanggaoguanli",
          "orderNum": 0,
          "isShow": true,
          "delFlag": 0,
          "createdBy": null,
          "updatedBy": null,
          "level": 2,
          "parentName": "市场运营",
          "children": []
        }
      ]
    },
    {
      "id": 158,
      "name": "促销管理",
      "parentId": 0,
      "url": "",
      "perms": "",
      "type": 0,
      "icon": "el-icon-ali-cuxiaoguanli",
      "orderNum": 6,
      "isShow": true,
      "delFlag": 0,
      "createdBy": null,
      "updatedBy": null,
      "level": 1,
      "children": [
        {
          "id": 159,
          "name": "团购秒杀",
          "parentId": 158,
          "url": "promotion/group_seckiller.vue",
          "perms": "promotion:group_seckiller",
          "type": 1,
          "icon": "el-icon-ali-yingxiaogongju-tuangoumiaosha",
          "orderNum": 0,
          "isShow": true,
          "delFlag": 0,
          "createdBy": null,
          "updatedBy": null,
          "level": 2,
          "parentName": "促销管理",
          "children": []
        },
        {
          "id": 160,
          "name": "促销列表",
          "parentId": 158,
          "url": "promotion/index.vue",
          "perms": "promotion",
          "type": 1,
          "icon": "el-icon-ali-cuxiao",
          "orderNum": 0,
          "isShow": true,
          "delFlag": 0,
          "createdBy": null,
          "updatedBy": null,
          "level": 2,
          "parentName": "促销管理",
          "children": []
        },
        {
          "id": 161,
          "name": "优惠券",
          "parentId": 158,
          "url": "promotion/coupon.vue",
          "perms": "promotion:coupon",
          "type": 1,
          "icon": "el-icon-ali-youhuiquan1",
          "orderNum": 0,
          "isShow": true,
          "delFlag": 0,
          "createdBy": null,
          "updatedBy": null,
          "level": 2,
          "parentName": "促销管理",
          "children": []
        }
      ]
    },
    {
      "id": 164,
      "name": "报表统计",
      "parentId": 0,
      "url": "",
      "perms": "",
      "type": 0,
      "icon": "el-icon-ali-baobiaotongji",
      "orderNum": 7,
      "isShow": true,
      "delFlag": 0,
      "createdBy": null,
      "updatedBy": null,
      "level": 1,
      "children": [
        {
          "id": 165,
          "name": "用户收藏",
          "parentId": 164,
          "url": "report/goods_collection.vue",
          "perms": "report:goods_collection",
          "type": 1,
          "icon": "el-icon-ali-starred",
          "orderNum": 0,
          "isShow": true,
          "delFlag": 0,
          "createdBy": null,
          "updatedBy": null,
          "level": 2,
          "parentName": "报表统计",
          "children": []
        },
        {
          "id": 166,
          "name": "订单销量",
          "parentId": 164,
          "url": "report/order.vue",
          "perms": "report:order",
          "type": 1,
          "icon": "el-icon-ali-dingdan",
          "orderNum": 0,
          "isShow": true,
          "delFlag": 0,
          "createdBy": null,
          "updatedBy": null,
          "level": 2,
          "parentName": "报表统计",
          "children": []
        },
        {
          "id": 167,
          "name": "财务收款",
          "parentId": 164,
          "url": "report/pay.vue",
          "perms": "report:pay",
          "type": 1,
          "icon": "el-icon-ali-caiwushoukuan",
          "orderNum": 0,
          "isShow": true,
          "delFlag": 0,
          "createdBy": null,
          "updatedBy": null,
          "level": 2,
          "parentName": "报表统计",
          "children": []
        },
        {
          "id": 168,
          "name": "商品销量",
          "parentId": 164,
          "url": "report/goods_sale.vue",
          "perms": "report:goods_sale",
          "type": 1,
          "icon": "el-icon-ali-shangpinxiaoliangfenxi",
          "orderNum": 0,
          "isShow": true,
          "delFlag": 0,
          "createdBy": null,
          "updatedBy": null,
          "level": 2,
          "parentName": "报表统计",
          "children": []
        }
      ]
    },
    {
      "id": 169,
      "name": "微信管理",
      "parentId": 0,
      "url": "",
      "perms": "",
      "type": 0,
      "icon": "el-icon-ali--",
      "orderNum": 8,
      "isShow": true,
      "delFlag": 0,
      "createdBy": null,
      "updatedBy": null,
      "level": 1,
      "children": [
        {
          "id": 170,
          "name": "公众号菜单",
          "parentId": 169,
          "url": "wechat/edit_menu.vue",
          "perms": "wechat:edit_menu",
          "type": 1,
          "icon": "el-icon-ali-gongzhonghaocaidanpeizhi",
          "orderNum": 0,
          "isShow": true,
          "delFlag": 0,
          "createdBy": null,
          "updatedBy": null,
          "level": 2,
          "parentName": "微信管理",
          "children": []
        },
        {
          "id": 171,
          "name": "公众号配置",
          "parentId": 169,
          "url": "wechat/mp_setting.vue",
          "perms": "wechat:mp_setting",
          "type": 1,
          "icon": "el-icon-ali-gongzhonghaopeizhi",
          "orderNum": 0,
          "isShow": true,
          "delFlag": 0,
          "createdBy": null,
          "updatedBy": null,
          "level": 2,
          "parentName": "微信管理",
          "children": []
        },
        {
          "id": 172,
          "name": "模板列表",
          "parentId": 169,
          "url": "wechat/template.vue",
          "perms": "wechat:template",
          "type": 1,
          "icon": "el-icon-ali-mobanliebiao",
          "orderNum": 0,
          "isShow": true,
          "delFlag": 0,
          "createdBy": null,
          "updatedBy": null,
          "level": 2,
          "parentName": "微信管理",
          "children": []
        },
        {
          "id": 173,
          "name": "小程序配置",
          "parentId": 169,
          "url": "wechat/miniprogram_setting.vue",
          "perms": "wechat:miniprogram_setting",
          "type": 1,
          "icon": "el-icon-ali-xiaochengxupeizhi",
          "orderNum": 0,
          "isShow": true,
          "delFlag": 0,
          "createdBy": null,
          "updatedBy": null,
          "level": 2,
          "parentName": "微信管理",
          "children": []
        },
        {
          "id": 174,
          "name": "微信消息管理",
          "parentId": 169,
          "url": "wechat/message.vue",
          "perms": "wechat:message",
          "type": 1,
          "icon": "el-icon-ali-xiaoxi",
          "orderNum": 0,
          "isShow": true,
          "delFlag": 0,
          "createdBy": null,
          "updatedBy": null,
          "level": 2,
          "parentName": "微信管理",
          "children": []
        }
      ]
    },
    {
      "id": 321,
      "name": "智能表单",
      "parentId": 0,
      "url": "",
      "perms": "",
      "type": 0,
      "icon": "el-icon-ali-zhinengbiaodan",
      "orderNum": 9,
      "isShow": true,
      "delFlag": 0,
      "createdBy": null,
      "updatedBy": null,
      "level": 1,
      "children": [
        {
          "id": 323,
          "name": "表单列表",
          "parentId": 321,
          "url": "form/index.vue",
          "perms": "form",
          "type": 1,
          "icon": "el-icon-ali-biaodan",
          "orderNum": 0,
          "isShow": true,
          "delFlag": 0,
          "createdBy": null,
          "updatedBy": null,
          "level": 2,
          "parentName": "智能表单",
          "children": []
        },
        {
          "id": 322,
          "name": "提交列表",
          "parentId": 321,
          "url": "form/form_submit.vue",
          "perms": "form:form_submit",
          "type": 1,
          "icon": "el-icon-ali-tijiao",
          "orderNum": 1,
          "isShow": true,
          "delFlag": 0,
          "createdBy": null,
          "updatedBy": null,
          "level": 2,
          "parentName": "智能表单",
          "children": []
        }
      ]
    },
    {
      "id": 329,
      "name": "页面管理",
      "parentId": 0,
      "url": "",
      "perms": "",
      "type": 0,
      "icon": "el-icon-ali-yemiansheji",
      "orderNum": 10,
      "isShow": true,
      "delFlag": 0,
      "createdBy": null,
      "updatedBy": null,
      "level": 1,
      "children": [
        {
          "id": 330,
          "name": "布局管理",
          "parentId": 329,
          "url": "page/index.vue",
          "perms": "page",
          "type": 1,
          "icon": "el-icon-ali-bujuguanli",
          "orderNum": 0,
          "isShow": true,
          "delFlag": 0,
          "createdBy": null,
          "updatedBy": null,
          "level": 2,
          "parentName": "页面管理",
          "children": []
        }
      ]
    },
    {
      "id": 35,
      "name": "地址测试",
      "parentId": 0,
      "url": "demo.vue",
      "perms": "",
      "type": 1,
      "icon": "el-icon-ali-ceshi",
      "orderNum": 11,
      "isShow": true,
      "delFlag": 0,
      "createdBy": null,
      "updatedBy": null,
      "level": 1,
      "children": []
    }
  ]